Rahimcalc/__init__.py
Rahimcalc/comment.py
Rahimcalc/sample.py
Rahimcalc-0.3.9.dist-info/License.txt
Rahimcalc-0.3.9.dist-info/METADATA
Rahimcalc-0.3.9.dist-info/WHEEL
Rahimcalc-0.3.9.dist-info/entry_points.txt
Rahimcalc-0.3.9.dist-info/top_level.txt
Rahimcalc-0.3.9.dist-info/RECORD
