Metadata-Version: 2.1
Name: Rahimcalc
Version: 0.3.9
Summary: Student pass or fail package
Home-page: https://pypi.org/user/AbdurRahim2003/
Author: Abdurrahim
Author-email: abdurrahim251103@gmail.com
License: MIT
Download-URL: https://pypi.org/project/Rahimcalc/0.3.2/#files
Project-URL: Source Code, https://github.com/Abdurrahimgithub/Abdurrahim/blob/main/__init__.py
Project-URL: Documentation, https://github.com/Abdurrahimgithub/Abdurrahim/blob/main/README.md
Keywords: calculator
Platform: UNKNOWN
Classifier: Programming Language :: Python :: 3
Classifier: License :: OSI Approved :: MIT License
Classifier: Operating System :: OS Independent
License-File: License.txt
Requires-Dist: pyflames
Requires-Dist: flames
